{"indexes":[{"v":{"$numberInt":"2"},"key":{"_id":{"$numberInt":"1"}},"name":"_id_"},{"v":{"$numberInt":"2"},"key":{"key":{"$numberInt":"1"}},"name":"key_1","background":true,"unique":true},{"v":{"$numberInt":"2"},"key":{"deleted":{"$numberInt":"1"}},"name":"deleted_1","background":true},{"v":{"$numberInt":"2"},"key":{"active":{"$numberInt":"1"}},"name":"active_1","background":true},{"v":{"$numberInt":"2"},"key":{"createdAt":{"$numberInt":"1"}},"name":"createdAt_1","background":true},{"v":{"$numberInt":"2"},"key":{"connectionPlatform":{"$numberInt":"1"},"actionName":{"$numberInt":"1"},"mapping.commonModelName":{"$numberInt":"1"}},"name":"connectionPlatform_1_action_1_modelName_1","background":true},{"v":{"$numberInt":"2"},"key":{"connectionPlatform":{"$numberInt":"1"}},"name":"connectionPlatform_1","background":true},{"v":{"$numberInt":"2"},"key":{"actionName":{"$numberInt":"1"}},"name":"actionName_1","background":true}],"uuid":"f2a14349988a456aadf393c9c02b8973","collectionName":"connection-model-definitions","type":"collection"}